{
  "tr_code": "SC4",
  "tr_name": "주식주문거부",
  "protocol": "websocket",
  "is_websocket": true,
  "endpoint_path": "/websocket/stock",
  "api_group_id": "9a2800c3-9bf2-4d67-8d83-905074f06646",
  "source_group_name": "[주식] 실시간 시세",
  "request_blocks": [
    {
      "direction": "request",
      "block_name": "request_header",
      "field_index": 0,
      "field_name": "token",
      "korean_name": "접근토큰",
      "type": "String",
      "length": 1000,
      "required": true,
      "description_hash": "ee5c73906207dffe"
    },
    {
      "direction": "request",
      "block_name": "request_header",
      "field_index": 1,
      "field_name": "tr_type",
      "korean_name": "거래 Type",
      "type": "String",
      "length": 1,
      "required": true,
      "description_hash": "5d9761ebdce44e7f"
    },
    {
      "direction": "request",
      "block_name": "request_body",
      "field_index": 0,
      "field_name": "tr_cd",
      "korean_name": "거래 CD",
      "type": "String",
      "length": 3,
      "required": true,
      "description_hash": "4927a2d7cd706e4e"
    },
    {
      "direction": "request",
      "block_name": "request_body",
      "field_index": 1,
      "field_name": "tr_key",
      "korean_name": "단축코드",
      "type": "String",
      "length": 8,
      "required": false,
      "description_hash": "f8838dd2d41e179b"
    }
  ],
  "response_blocks": [
    {
      "direction": "response",
      "block_name": "response_header",
      "field_index": 0,
      "field_name": "tr_cd",
      "korean_name": "거래 CD",
      "type": "String",
      "length": 3,
      "required": true,
      "description_hash": "4927a2d7cd706e4e"
    }
  ],
  "rate_source_group": "9a2800c3-9bf2-4d67-8d83-905074f06646"
}
